{
  "workspaces": [
    {
      "id": "main",
      "name": "Rafael",
      "color": "#6366f1",
      "icon": "\ud83d\udc64",
      "projects": [
        "lead-lasso",
        "sheet-show"
      ]
    },
    {
      "id": "ion",
      "name": "Ion CRM",
      "color": "#10b981",
      "icon": "\ud83d\udcf1",
      "projects": [
        "ion-crm"
      ]
    }
  ],
  "projects": [
    {
      "id": "lead-lasso",
      "name": "Lead Lasso",
      "workspace": "main",
      "status": "active",
      "description": "AI lead generation",
      "tasks": [
        {
          "id": 1,
          "title": "Landing page copy (Portuguese + English)",
          "status": "todo",
          "priority": "medium"
        },
        {
          "id": 2,
          "title": "Cold outreach email sequences (3-touch)",
          "status": "todo",
          "priority": "medium"
        },
        {
          "id": 3,
          "title": "WhatsApp outreach templates",
          "status": "todo",
          "priority": "medium"
        },
        {
          "id": 4,
          "title": "Prospect qualification criteria",
          "status": "todo",
          "priority": "medium"
        },
        {
          "id": 5,
          "title": "Ideal Customer Profile documentation",
          "status": "todo",
          "priority": "medium"
        }
      ],
      "agents": [
        "research-lead"
      ]
    },
    {
      "id": "sheet-show",
      "name": "Sheet Show",
      "workspace": "main",
      "status": "active",
      "description": "AI data analysis",
      "tasks": [
        {
          "id": 1,
          "title": "Connect Stripe",
          "status": "todo",
          "priority": "high"
        },
        {
          "id": 2,
          "title": "Email service",
          "status": "todo",
          "priority": "high"
        }
      ],
      "agents": [
        "data-analyzer"
      ]
    },
    {
      "id": "ion-crm",
      "name": "Ion CRM",
      "workspace": "ion",
      "status": "active",
      "description": "Lead tracking",
      "tasks": [
        {
          "id": 1,
          "title": "Process leads",
          "status": "in-progress",
          "priority": "high"
        }
      ],
      "agents": [
        "ion-assistant"
      ]
    }
  ],
  "agents": {
    "research-lead": {
      "name": "Research Lead",
      "project": "lead-lasso",
      "status": "idle",
      "task": null
    },
    "outreach-bot": {
      "name": "Outreach Bot",
      "project": "lead-lasso",
      "status": "working",
      "task": "Building sequences"
    },
    "data-analyzer": {
      "name": "Data Analyzer",
      "project": "sheet-show",
      "status": "idle",
      "task": null
    },
    "ion-assistant": {
      "name": "Ion Assistant",
      "project": "ion-crm",
      "status": "waiting",
      "task": "Awaiting input"
    }
  },
  "calendar": [
    {
      "date": "2026-04-09",
      "title": "Review progress",
      "type": "reminder"
    },
    {
      "date": "2026-04-10",
      "title": "Call Ion",
      "type": "meeting"
    },
    {
      "date": "2026-04-11",
      "title": "Client delivery",
      "type": "deadline"
    }
  ],
  "documents": [
    {
      "title": "tech-architecture",
      "category": "technical",
      "project": "lead-lasso",
      "date": "2026-04-09"
    },
    {
      "title": "landing-page-copy",
      "category": "technical",
      "project": "lead-lasso",
      "date": "2026-04-09"
    },
    {
      "title": "strategy",
      "category": "strategy",
      "project": "lead-lasso",
      "date": "2026-04-09"
    },
    {
      "title": "outreach-sequences",
      "category": "technical",
      "project": "lead-lasso",
      "date": "2026-04-09"
    },
    {
      "title": "icp",
      "category": "technical",
      "project": "lead-lasso",
      "date": "2026-04-09"
    },
    {
      "title": "social-media-feature",
      "category": "technical",
      "project": "lead-lasso",
      "date": "2026-04-09"
    },
    {
      "title": "tech-specs",
      "category": "technical",
      "project": "lead-lasso",
      "date": "2026-04-09"
    },
    {
      "title": "README",
      "category": "technical",
      "project": "lead-lasso",
      "date": "2026-04-09"
    },
    {
      "title": "action-plan",
      "category": "technical",
      "project": "lead-lasso",
      "date": "2026-04-09"
    },
    {
      "title": "SHEPARD_PERSONA",
      "category": "technical",
      "project": "sheet-show",
      "date": "2026-04-09"
    }
  ]
}